compspec_ior/__init__.py
compspec_ior/defaults.py
compspec_ior/plugin.py
compspec_ior/schema.json
compspec_ior/version.py
compspec_ior-0.0.1.dist-info/LICENSE
compspec_ior-0.0.1.dist-info/METADATA
compspec_ior-0.0.1.dist-info/NOTICE
compspec_ior-0.0.1.dist-info/WHEEL
compspec_ior-0.0.1.dist-info/top_level.txt
compspec_ior-0.0.1.dist-info/RECORD
