Metadata-Version: 2.1
Name: compspec-ior
Version: 0.0.1
Summary: Compatibility specification and extractor plugin for IOR (I/O)
Home-page: https://github.com/compspec/compspec-ior
Author: Vanessa Sochat
Author-email: vsoch@users.noreply.github.com
Maintainer: Vanessa Sochat
License: LICENSE
Keywords: compatibility,compspec,IOR,I/O,intents
Classifier: Intended Audience :: Science/Research
Classifier: Intended Audience :: Developers
Classifier: License :: OSI Approved :: MIT License
Classifier: Programming Language :: Python
Classifier: Topic :: Software Development
Classifier: Topic :: Scientific/Engineering
Classifier: Operating System :: Unix
Classifier: Programming Language :: Python :: 3.10
License-File: LICENSE
License-File: NOTICE
Requires-Dist: compspec (>=0.1.0)
Provides-Extra: all
Requires-Dist: compspec (>=0.1.0) ; extra == 'all'
Requires-Dist: pytest (>=4.6.2) ; extra == 'all'
